rewardifycli/__init__.py
rewardifycli/install.py
rewardifycli/inventory.py
rewardifycli/login.py
rewardifycli/main.py
rewardifycli/packs.py
rewardifycli/rewards.py
rewardifycli/update.py
rewardifycli/users.py
rewardifycli/util.py
rewardifycli/__internal/__init__.py
rewardifycli/__internal/tests.py
rewardifycli/__internal/util.py
rewardifycli/templates/install.jinja2
rewardifycli/templates/inventory.jinja2
rewardifycli/templates/login_success.jinja2
rewardifycli/templates/no_user.jinja2
rewardifycli/templates/pack_bought.jinja2
rewardifycli/templates/pack_list.jinja2
rewardifycli/templates/pack_opened.jinja2
rewardifycli/templates/permission_buy_error.jinja2
rewardifycli/templates/permission_use_error.jinja2
rewardifycli/templates/reward_bought.jinja2
rewardifycli/templates/reward_list.jinja2
rewardifycli/templates/reward_recycled.jinja2
rewardifycli/templates/reward_used.jinja2
rewardifycli/templates/updated.jinja2
rewardifycli/templates/user_created.jinja2
rewardifycli/templates/user_not_exists.jinja2
rewardifycli/templates/wrong_password.jinja2
rewardifycli-0.1.0.dist-info/DESCRIPTION.rst
rewardifycli-0.1.0.dist-info/METADATA
rewardifycli-0.1.0.dist-info/RECORD
rewardifycli-0.1.0.dist-info/WHEEL
rewardifycli-0.1.0.dist-info/entry_points.txt
rewardifycli-0.1.0.dist-info/metadata.json
rewardifycli-0.1.0.dist-info/top_level.txt
