Metadata-Version: 2.0
Name: rewardifycli
Version: 0.1.0
Summary: CLI interface for rewardify package
Home-page: https://github.com/the16thpythonist/rewardifycli
Author: Jonas Teufel
Author-email: jonseb1998@gmail.com
License: BSD license
Keywords: rewardifycli
Platform: UNKNOWN
Classifier: Development Status :: 2 - Pre-Alpha
Classifier: Intended Audience :: Developers
Classifier: License :: OSI Approved :: BSD License
Classifier: Natural Language :: English
Classifier: Programming Language :: Python :: 2
Classifier: Programming Language :: Python :: 2.7
Classifier: Programming Language :: Python :: 3
Classifier: Programming Language :: Python :: 3.4
Classifier: Programming Language :: Python :: 3.5
Classifier: Programming Language :: Python :: 3.6
Classifier: Programming Language :: Python :: 3.7
Requires-Dist: Click (>=6.0)
Requires-Dist: rewardify
